drbpackagetesting/__init__.py
drbpackagetesting/consoletest.py
drbpackagetesting-0.0.0.dev8.dist-info/LICENSE.md
drbpackagetesting-0.0.0.dev8.dist-info/METADATA
drbpackagetesting-0.0.0.dev8.dist-info/WHEEL
drbpackagetesting-0.0.0.dev8.dist-info/entry_points.txt
drbpackagetesting-0.0.0.dev8.dist-info/top_level.txt
drbpackagetesting-0.0.0.dev8.dist-info/RECORD
