Metadata-Version: 2.1
Name: drbpackagetesting
Version: 0.0.0.dev8
Summary: Package Build Testing
Home-page: https://github.com/baxterda/packagetesting
Author: Dawson Baxter
Author-email: dbaxtersoftware@gmail.com
License: MIT
Platform: UNKNOWN
Classifier: License :: OSI Approved :: MIT License
Requires-Python: >=3.6
License-File: LICENSE.md
